mktdt.py
marketdt-0.0.5.dist-info/METADATA
marketdt-0.0.5.dist-info/WHEEL
marketdt-0.0.5.dist-info/top_level.txt
marketdt-0.0.5.dist-info/RECORD
