Metadata-Version: 2.1
Name: marketdt
Version: 0.0.5
Summary: Market-oriented datetime functions (currently only NYSE)
Home-page: UNKNOWN
Author: UNKNOWN
Author-email: UNKNOWN
License: UNKNOWN
Platform: UNKNOWN
